edc_crf/__init__.py
edc_crf/admin_site.py
edc_crf/apps.py
edc_crf/auths.py
edc_crf/crf_form_validator.py
edc_crf/crf_form_validator_mixins.py
edc_crf/fieldset.py
edc_crf/form_validator_mixins.py
edc_crf/update_crf_status_command.py
edc_crf/update_crf_status_for_instance.py
edc_crf/urls.py
edc_crf/utils.py
edc_crf/admin/__init__.py
edc_crf/admin/crf_status_admin.py
edc_crf/locale/sw/LC_MESSAGES/django.mo
edc_crf/locale/sw/LC_MESSAGES/django.po
edc_crf/management/commands/update_crf_status.py
edc_crf/management/commands/__pycache__/update_crf_status.cpython-38.pyc
edc_crf/migrations/0001_initial.py
edc_crf/migrations/0002_auto_20200729_2310.py
edc_crf/migrations/0003_alter_crfstatus_options.py
edc_crf/migrations/0004_alter_crfstatus_device_created_and_more.py
edc_crf/migrations/0005_alter_crfstatus_options_crfstatus_locale_created_and_more.py
edc_crf/migrations/0006_remove_crfstatus_edc_crf_crf_modifie_6152c9_idx_and_more.py
edc_crf/migrations/0007_crfstatus_edc_crf_crf_subject_e09e96_idx_and_more.py
edc_crf/migrations/__init__.py
edc_crf/model_mixins/__init__.py
edc_crf/model_mixins/crf_inline_model_mixin.py
edc_crf/model_mixins/crf_model_mixin.py
edc_crf/model_mixins/crf_no_manager_model_mixin.py
edc_crf/model_mixins/crf_status_model_mixin.py
edc_crf/model_mixins/crf_with_action_model_mixin.py
edc_crf/model_mixins/singleton_crf_model_mixin.py
edc_crf/modeladmin_mixins/__init__.py
edc_crf/modeladmin_mixins/crf_model_admin.py
edc_crf/modeladmin_mixins/crf_status_model_admin_mixin.py
edc_crf/modelform_mixins/__init__.py
edc_crf/modelform_mixins/crf_model_form_mixin.py
edc_crf/modelform_mixins/crf_singleton_model_form_mixin.py
edc_crf/modelform_mixins/inline_model_form_mixin.py
edc_crf/modelform_mixins/requisition_model_form_mixin.py
edc_crf/models/__init__.py
edc_crf/models/crf_status.py
edc_crf/models/signals.py
edc_crf/tests/__init__.py
edc_crf/tests/consents.py
edc_crf/tests/holidays.csv
edc_crf/tests/models.py
edc_crf/tests/test_settings.py
edc_crf-1.0.2.dist-info/licenses/AUTHORS.rst
edc_crf-1.0.2.dist-info/licenses/LICENSE
edc_crf-1.0.2.dist-info/METADATA
edc_crf-1.0.2.dist-info/WHEEL
edc_crf-1.0.2.dist-info/top_level.txt
edc_crf-1.0.2.dist-info/RECORD
